conf_templater/__init__.py
conf_templater/cli.py
conf_templater/console.py
conf_templater/exc.py
conf_templater/py.typed
conf_templater/template.py
conf_templater-0.2.0.dist-info/entry_points.txt
conf_templater-0.2.0.dist-info/LICENSE.txt
conf_templater-0.2.0.dist-info/WHEEL
conf_templater-0.2.0.dist-info/METADATA
conf_templater-0.2.0.dist-info/RECORD
